pystablemotifs/Attractor.py
pystablemotifs/AttractorRepertoire.py
pystablemotifs/__init__.py
pystablemotifs/__main__.py
pystablemotifs/drivers.py
pystablemotifs/export.py
pystablemotifs/format.py
pystablemotifs/random_boolean_networks.py
pystablemotifs/reduction.py
pystablemotifs/restrict_space.py
pystablemotifs/succession.py
pystablemotifs/time_reversal.py
pystablemotifs-3.0.6.dist-info/LICENSE
pystablemotifs-3.0.6.dist-info/METADATA
pystablemotifs-3.0.6.dist-info/WHEEL
pystablemotifs-3.0.6.dist-info/top_level.txt
pystablemotifs-3.0.6.dist-info/RECORD
