Metadata-Version: 2.1
Name: pystablemotifs
Version: 3.0.6
Summary: Python package for analyzing Boolean Netowrk
Home-page: https://github.com/jcrozum/pystablemotifs
Author: Jordan Rozum
Author-email: jcr52@psu.edu
License: MIT
Platform: UNKNOWN
Requires-Python: >=3.5
License-File: LICENSE
Requires-Dist: matplotlib (>=3.2.1)
Requires-Dist: networkx (>=2.4.0)
Requires-Dist: numpy (>=1.19.2)
Requires-Dist: pandas (>=1.0.0)
Requires-Dist: sympy (>=1.5.1)
